{
  "Profiles": [
    {
      "Tablet": "Huion H640P",
      "OutputMode": {
        "Path": "OpenTabletDriver.Desktop.Output.LinuxArtistMode",
        "Settings": [],
        "Enable": true
      },
      "Filters": [
        {
          "Path": "slimy_scylla.slimy_scylla_position_smoothing_moving_average",
          "Settings": [
            {
              "Property": "amount",
              "Value": 10
            },
            {
              "Property": "catch_up",
              "Value": true
            },
            {
              "Property": "pressure_deadzone_percent",
              "Value": null
            },
            {
              "Property": "remove_tail_position_reports",
              "Value": 1
            },
            {
              "Property": "leak_smoothing_to_hover",
              "Value": null
            },
            {
              "Property": "always_apply_to_hover",
              "Value": null
            },
            {
              "Property": "never_intercept_pressure_on_off",
              "Value": null
            }
          ],
          "Enable": true
        },
        {
          "Path": "slimy_scylla.slimy_scylla_pressure_curve",
          "Settings": [
            {
              "Property": "gain",
              "Value": 1.0
            },
            {
              "Property": "softness",
              "Value": 0.0
            },
            {
              "Property": "minimum_value_percent",
              "Value": 0.0
            },
            {
              "Property": "maximum_value_percent",
              "Value": 100.0
            },
            {
              "Property": "invert",
              "Value": null
            },
            {
              "Property": "pressure_deadzone_percent",
              "Value": null
            }
          ],
          "Enable": false
        },
        {
          "Path": "slimy_scylla.slimy_scylla_pressure_processing_fixed_value",
          "Settings": [
            {
              "Property": "value_percent",
              "Value": 22.0
            },
            {
              "Property": "pressure_deadzone_percent",
              "Value": null
            },
            {
              "Property": "remove_tail_pressure_reports",
              "Value": 1
            }
          ],
          "Enable": false
        },
        {
          "Path": "slimy_scylla.slimy_scylla_pressure_processing_sample_and_hold",
          "Settings": [
            {
              "Property": "sample_number",
              "Value": 15
            },
            {
              "Property": "pressure_deadzone_percent",
              "Value": null
            },
            {
              "Property": "remove_tail_pressure_reports",
              "Value": 1
            }
          ],
          "Enable": false
        },
        {
          "Path": "slimy_scylla.slimy_scylla_dynamic_weighted",
          "Settings": [
            {
              "Property": "drag",
              "Value": 0.2
            },
            {
              "Property": "mass",
              "Value": 31.25
            },
            {
              "Property": "max_pressure_speed",
              "Value": 20.0
            },
            {
              "Property": "pressure_deadzone_percent",
              "Value": null
            },
            {
              "Property": "remove_tail_pressure_reports",
              "Value": 1
            }
          ],
          "Enable": false
        },
        {
          "Path": "slimy_scylla.slimy_scylla_pressure_processing_moving_average",
          "Settings": [
            {
              "Property": "amount",
              "Value": 10
            },
            {
              "Property": "pressure_deadzone_percent",
              "Value": null
            },
            {
              "Property": "remove_tail_pressure_reports",
              "Value": 1
            }
          ],
          "Enable": false
        },
        {
          "Path": "slimy_scylla.slimy_scylla_pressure_processing_exponential_moving_average",
          "Settings": [
            {
              "Property": "amount",
              "Value": 0.1
            },
            {
              "Property": "pressure_deadzone_percent",
              "Value": null
            },
            {
              "Property": "remove_tail_pressure_reports",
              "Value": 1
            }
          ],
          "Enable": true
        }
      ],
      "AbsoluteModeSettings": {
        "Display": {
          "Width": 2560.0,
          "Height": 1080.0,
          "X": 1280.0,
          "Y": 540.0,
          "Rotation": 0.0
        },
        "Tablet": {
          "Width": 160.0,
          "Height": 100.0,
          "X": 80.0,
          "Y": 50.0,
          "Rotation": 0.0
        },
        "EnableClipping": true,
        "EnableAreaLimiting": false,
        "LockAspectRatio": false
      },
      "RelativeModeSettings": {
        "XSensitivity": 10.0,
        "YSensitivity": 10.0,
        "RelativeRotation": 0.0,
        "RelativeResetDelay": "00:00:00.1000000"
      },
      "Bindings": {
        "TipActivationThreshold": 0.0,
        "TipButton": {
          "Path": "OpenTabletDriver.Desktop.Binding.MouseBinding",
          "Settings": [
            {
              "Property": "Button",
              "Value": "Left"
            }
          ],
          "Enable": true
        },
        "EraserActivationThreshold": 0.0,
        "EraserButton": null,
        "PenButtons": [
          {
            "Path": "OpenTabletDriver.Desktop.Binding.KeyBinding",
            "Settings": [
              {
                "Property": "Key",
                "Value": "E"
              }
            ],
            "Enable": true
          },
          {
            "Path": "OpenTabletDriver.Desktop.Binding.KeyBinding",
            "Settings": [
              {
                "Property": "Key",
                "Value": "M"
              }
            ],
            "Enable": true
          }
        ],
        "AuxButtons": [
          {
            "Path": "OpenTabletDriver.Desktop.Binding.MultiKeyBinding",
            "Settings": [
              {
                "Property": "Keys",
                "Value": "Control+S"
              }
            ],
            "Enable": true
          },
          {
            "Path": "OpenTabletDriver.Desktop.Binding.MultiKeyBinding",
            "Settings": [
              {
                "Property": "Keys",
                "Value": "Control+Equal"
              }
            ],
            "Enable": true
          },
          {
            "Path": "OpenTabletDriver.Desktop.Binding.MultiKeyBinding",
            "Settings": [
              {
                "Property": "Keys",
                "Value": "Control+Minus"
              }
            ],
            "Enable": true
          },
          {
            "Path": "OpenTabletDriver.Desktop.Binding.KeyBinding",
            "Settings": [
              {
                "Property": "Key",
                "Value": "RightBracket"
              }
            ],
            "Enable": true
          },
          {
            "Path": "OpenTabletDriver.Desktop.Binding.KeyBinding",
            "Settings": [
              {
                "Property": "Key",
                "Value": "LeftBracket"
              }
            ],
            "Enable": true
          },
          {
            "Path": "OpenTabletDriver.Desktop.Binding.MultiKeyBinding",
            "Settings": [
              {
                "Property": "Keys",
                "Value": "Control+Z"
              }
            ],
            "Enable": true
          }
        ],
        "MouseButtons": [],
        "MouseScrollUp": null,
        "MouseScrollDown": null
      }
    }
  ],
  "LockUsableAreaDisplay": true,
  "LockUsableAreaTablet": true,
  "Tools": []
}